draw_lines/__init__.py
draw_lines/frontend/build/asset-manifest.json
draw_lines/frontend/build/bootstrap.min.css
draw_lines/frontend/build/index.html
draw_lines/frontend/build/static/js/main.7c953a0a.js
draw_lines/frontend/build/static/js/main.7c953a0a.js.LICENSE.txt
draw_lines/frontend/build/static/js/main.7c953a0a.js.map
streamlit_draw_line-0.0.1.dist-info/METADATA
streamlit_draw_line-0.0.1.dist-info/WHEEL
streamlit_draw_line-0.0.1.dist-info/top_level.txt
streamlit_draw_line-0.0.1.dist-info/RECORD
