Metadata-Version: 2.1
Name: streamlit-draw-line
Version: 0.0.1
Home-page: 
Author: 
Author-email: 
Requires-Python: >=3.9
Requires-Dist: streamlit (>=0.66)
Provides-Extra: devel
Requires-Dist: wheel ; extra == 'devel'
Requires-Dist: pytest (==7.4.0) ; extra == 'devel'
Requires-Dist: playwright (==1.39.0) ; extra == 'devel'
Requires-Dist: requests (==2.31.0) ; extra == 'devel'
Requires-Dist: pytest-playwright-snapshot (==1.0) ; extra == 'devel'
Requires-Dist: pytest-rerunfailures (==12.0) ; extra == 'devel'
